[{"date":"2017-01-23","store_id":1966.0,"total_sales":0.03,"total_items_sold":1.0,"number_of_tickets":1,"number_of_unique_items":1,"is_outlier":false},{"date":"2017-01-24","store_id":1966.0,"total_sales":1204.5,"total_items_sold":99.0,"number_of_tickets":95,"number_of_unique_items":65,"is_outlier":false},{"date":"2017-01-25","store_id":1966.0,"total_sales":1804.5,"total_items_sold":150.0,"number_of_tickets":145,"number_of_unique_items":84,"is_outlier":false},{"date":"2017-01-26","store_id":1966.0,"total_sales":1864.75,"total_items_sold":150.0,"number_of_tickets":136,"number_of_unique_items":73,"is_outlier":false},{"date":"2017-01-27","store_id":1966.0,"total_sales":3101.0,"total_items_sold":222.0,"number_of_tickets":187,"number_of_unique_items":97,"is_outlier":false},{"date":"2017-01-28","store_id":1966.0,"total_sales":3644.5,"total_items_sold":213.0,"number_of_tickets":181,"number_of_unique_items":95,"is_outlier":false},{"date":"2017-01-29","store_id":1966.0,"total_sales":1986.0,"total_items_sold":135.0,"number_of_tickets":126,"number_of_unique_items":71,"is_outlier":false},{"date":"2017-01-30","store_id":1966.0,"total_sales":2937.0,"total_items_sold":101.0,"number_of_tickets":90,"number_of_unique_items":56,"is_outlier":false},{"date":"2017-01-31","store_id":1966.0,"total_sales":1855.5,"total_items_sold":144.0,"number_of_tickets":138,"number_of_unique_items":82,"is_outlier":false},{"date":"2017-02-01","store_id":1966.0,"total_sales":1999.5,"total_items_sold":167.0,"number_of_tickets":152,"number_of_unique_items":89,"is_outlier":false},{"date":"2017-02-02","store_id":1966.0,"total_sales":6500.0,"total_items_sold":2.0,"number_of_tickets":2,"number_of_unique_items":2,"is_outlier":false},{"date":"2017-02-03","store_id":1966.0,"total_sales":3199.5,"total_items_sold":217.0,"number_of_tickets":194,"number_of_unique_items":105,"is_outlier":false},{"date":"2017-02-04","store_id":1966.0,"total_sales":2511.0,"total_items_sold":193.0,"number_of_tickets":179,"number_of_unique_items":94,"is_outlier":false},{"date":"2017-02-05","store_id":1966.0,"total_sales":1349.0,"total_items_sold":98.0,"number_of_tickets":89,"number_of_unique_items":53,"is_outlier":false},{"date":"2017-02-06","store_id":1966.0,"total_sales":1249.0,"total_items_sold":106.0,"number_of_tickets":101,"number_of_unique_items":71,"is_outlier":false},{"date":"2017-02-07","store_id":1966.0,"total_sales":2036.0,"total_items_sold":150.0,"number_of_tickets":133,"number_of_unique_items":76,"is_outlier":false},{"date":"2017-02-08","store_id":1966.0,"total_sales":1503.5,"total_items_sold":117.0,"number_of_tickets":98,"number_of_unique_items":66,"is_outlier":false},{"date":"2017-02-09","store_id":1966.0,"total_sales":1856.0,"total_items_sold":91.0,"number_of_tickets":84,"number_of_unique_items":61,"is_outlier":false},{"date":"2017-02-10","store_id":1966.0,"total_sales":3296.5,"total_items_sold":188.0,"number_of_tickets":162,"number_of_unique_items":97,"is_outlier":false},{"date":"2017-02-11","store_id":1966.0,"total_sales":2518.01,"total_items_sold":195.0,"number_of_tickets":176,"number_of_unique_items":107,"is_outlier":false},{"date":"2017-02-12","store_id":1966.0,"total_sales":9355.5,"total_items_sold":141.0,"number_of_tickets":133,"number_of_unique_items":84,"is_outlier":false},{"date":"2017-02-13","store_id":1966.0,"total_sales":1347.0,"total_items_sold":126.0,"number_of_tickets":116,"number_of_unique_items":79,"is_outlier":false},{"date":"2017-02-14","store_id":1966.0,"total_sales":2549.0,"total_items_sold":185.0,"number_of_tickets":166,"number_of_unique_items":92,"is_outlier":false},{"date":"2017-02-15","store_id":1966.0,"total_sales":1940.5,"total_items_sold":161.0,"number_of_tickets":138,"number_of_unique_items":88,"is_outlier":false},{"date":"2017-02-17","store_id":1966.0,"total_sales":2987.0,"total_items_sold":229.0,"number_of_tickets":207,"number_of_unique_items":111,"is_outlier":false},{"date":"2017-02-18","store_id":1966.0,"total_sales":2503.15,"total_items_sold":212.0,"number_of_tickets":182,"number_of_unique_items":106,"is_outlier":false},{"date":"2017-02-19","store_id":1966.0,"total_sales":2258.0,"total_items_sold":174.0,"number_of_tickets":159,"number_of_unique_items":91,"is_outlier":false},{"date":"2017-02-20","store_id":1966.0,"total_sales":2236.5,"total_items_sold":190.0,"number_of_tickets":163,"number_of_unique_items":96,"is_outlier":false},{"date":"2017-02-21","store_id":1966.0,"total_sales":1556.0,"total_items_sold":121.0,"number_of_tickets":111,"number_of_unique_items":66,"is_outlier":false},{"date":"2017-02-22","store_id":1966.0,"total_sales":2034.7,"total_items_sold":135.0,"number_of_tickets":128,"number_of_unique_items":80,"is_outlier":false},{"date":"2017-02-23","store_id":1966.0,"total_sales":3303.25,"total_items_sold":195.0,"number_of_tickets":154,"number_of_unique_items":97,"is_outlier":false},{"date":"2017-02-24","store_id":1966.0,"total_sales":3060.0,"total_items_sold":250.0,"number_of_tickets":223,"number_of_unique_items":123,"is_outlier":false},{"date":"2017-02-25","store_id":1966.0,"total_sales":2730.83,"total_items_sold":204.0,"number_of_tickets":190,"number_of_unique_items":107,"is_outlier":false},{"date":"2017-02-26","store_id":1966.0,"total_sales":1967.0,"total_items_sold":153.0,"number_of_tickets":142,"number_of_unique_items":78,"is_outlier":false},{"date":"2017-02-27","store_id":1966.0,"total_sales":1924.5,"total_items_sold":150.0,"number_of_tickets":135,"number_of_unique_items":80,"is_outlier":false},{"date":"2017-02-28","store_id":1966.0,"total_sales":1879.0,"total_items_sold":143.0,"number_of_tickets":129,"number_of_unique_items":72,"is_outlier":false},{"date":"2017-03-01","store_id":1966.0,"total_sales":1794.0,"total_items_sold":137.0,"number_of_tickets":122,"number_of_unique_items":74,"is_outlier":false},{"date":"2017-03-02","store_id":1966.0,"total_sales":2318.0,"total_items_sold":164.0,"number_of_tickets":153,"number_of_unique_items":87,"is_outlier":false},{"date":"2017-03-03","store_id":1966.0,"total_sales":2378.5,"total_items_sold":189.0,"number_of_tickets":164,"number_of_unique_items":98,"is_outlier":false},{"date":"2017-03-04","store_id":1966.0,"total_sales":2986.0,"total_items_sold":234.0,"number_of_tickets":199,"number_of_unique_items":107,"is_outlier":false},{"date":"2017-03-05","store_id":1966.0,"total_sales":2041.5,"total_items_sold":149.0,"number_of_tickets":131,"number_of_unique_items":82,"is_outlier":false},{"date":"2017-03-06","store_id":1966.0,"total_sales":1475.5,"total_items_sold":121.0,"number_of_tickets":104,"number_of_unique_items":68,"is_outlier":false},{"date":"2017-03-07","store_id":1966.0,"total_sales":1773.0,"total_items_sold":140.0,"number_of_tickets":118,"number_of_unique_items":83,"is_outlier":false},{"date":"2017-03-08","store_id":1966.0,"total_sales":1986.2,"total_items_sold":167.0,"number_of_tickets":146,"number_of_unique_items":101,"is_outlier":false},{"date":"2017-03-09","store_id":1966.0,"total_sales":3013.0,"total_items_sold":151.0,"number_of_tickets":143,"number_of_unique_items":93,"is_outlier":false},{"date":"2017-03-10","store_id":1966.0,"total_sales":2175.0,"total_items_sold":166.0,"number_of_tickets":151,"number_of_unique_items":86,"is_outlier":false},{"date":"2017-03-11","store_id":1966.0,"total_sales":3123.5,"total_items_sold":205.0,"number_of_tickets":167,"number_of_unique_items":94,"is_outlier":false},{"date":"2017-03-12","store_id":1966.0,"total_sales":1979.0,"total_items_sold":153.0,"number_of_tickets":144,"number_of_unique_items":88,"is_outlier":false},{"date":"2017-03-13","store_id":1966.0,"total_sales":1613.5,"total_items_sold":138.0,"number_of_tickets":115,"number_of_unique_items":77,"is_outlier":false},{"date":"2017-03-14","store_id":1966.0,"total_sales":382.0,"total_items_sold":22.0,"number_of_tickets":22,"number_of_unique_items":19,"is_outlier":false},{"date":"2017-03-15","store_id":1966.0,"total_sales":1466.5,"total_items_sold":118.0,"number_of_tickets":106,"number_of_unique_items":76,"is_outlier":false},{"date":"2017-03-16","store_id":1966.0,"total_sales":1998.25,"total_items_sold":149.0,"number_of_tickets":134,"number_of_unique_items":86,"is_outlier":false},{"date":"2017-03-17","store_id":1966.0,"total_sales":2459.5,"total_items_sold":200.0,"number_of_tickets":176,"number_of_unique_items":102,"is_outlier":false},{"date":"2017-03-18","store_id":1966.0,"total_sales":2569.0,"total_items_sold":190.0,"number_of_tickets":150,"number_of_unique_items":92,"is_outlier":false},{"date":"2017-03-19","store_id":1966.0,"total_sales":1971.0,"total_items_sold":144.0,"number_of_tickets":126,"number_of_unique_items":75,"is_outlier":false},{"date":"2017-03-20","store_id":1966.0,"total_sales":1812.5,"total_items_sold":141.0,"number_of_tickets":129,"number_of_unique_items":82,"is_outlier":false},{"date":"2017-03-21","store_id":1966.0,"total_sales":1829.0,"total_items_sold":149.0,"number_of_tickets":129,"number_of_unique_items":80,"is_outlier":false},{"date":"2017-03-22","store_id":1966.0,"total_sales":1833.0,"total_items_sold":143.0,"number_of_tickets":132,"number_of_unique_items":78,"is_outlier":false},{"date":"2017-03-23","store_id":1966.0,"total_sales":1944.0,"total_items_sold":148.0,"number_of_tickets":141,"number_of_unique_items":86,"is_outlier":false},{"date":"2017-03-24","store_id":1966.0,"total_sales":2554.5,"total_items_sold":224.0,"number_of_tickets":198,"number_of_unique_items":109,"is_outlier":false},{"date":"2017-03-25","store_id":1966.0,"total_sales":2782.5,"total_items_sold":208.0,"number_of_tickets":181,"number_of_unique_items":117,"is_outlier":false},{"date":"2017-03-26","store_id":1966.0,"total_sales":1767.5,"total_items_sold":131.0,"number_of_tickets":125,"number_of_unique_items":77,"is_outlier":false},{"date":"2017-03-27","store_id":1966.0,"total_sales":1082.0,"total_items_sold":89.0,"number_of_tickets":82,"number_of_unique_items":60,"is_outlier":false},{"date":"2017-03-28","store_id":1966.0,"total_sales":1893.5,"total_items_sold":146.0,"number_of_tickets":131,"number_of_unique_items":73,"is_outlier":false},{"date":"2017-03-29","store_id":1966.0,"total_sales":1792.5,"total_items_sold":155.0,"number_of_tickets":142,"number_of_unique_items":84,"is_outlier":false},{"date":"2017-03-30","store_id":1966.0,"total_sales":2038.0,"total_items_sold":157.0,"number_of_tickets":144,"number_of_unique_items":86,"is_outlier":false},{"date":"2017-03-31","store_id":1966.0,"total_sales":1839.05,"total_items_sold":142.0,"number_of_tickets":121,"number_of_unique_items":82,"is_outlier":false},{"date":"2017-04-01","store_id":1966.0,"total_sales":2958.6,"total_items_sold":195.0,"number_of_tickets":159,"number_of_unique_items":97,"is_outlier":false},{"date":"2017-04-02","store_id":1966.0,"total_sales":1867.53,"total_items_sold":158.0,"number_of_tickets":145,"number_of_unique_items":88,"is_outlier":false},{"date":"2017-04-03","store_id":1966.0,"total_sales":1665.5,"total_items_sold":130.0,"number_of_tickets":117,"number_of_unique_items":75,"is_outlier":false},{"date":"2017-04-04","store_id":1966.0,"total_sales":1504.5,"total_items_sold":116.0,"number_of_tickets":107,"number_of_unique_items":74,"is_outlier":false},{"date":"2017-04-05","store_id":1966.0,"total_sales":1917.5,"total_items_sold":151.0,"number_of_tickets":147,"number_of_unique_items":84,"is_outlier":false},{"date":"2017-04-06","store_id":1966.0,"total_sales":1839.0,"total_items_sold":135.0,"number_of_tickets":128,"number_of_unique_items":68,"is_outlier":false},{"date":"2017-04-07","store_id":1966.0,"total_sales":2134.5,"total_items_sold":167.0,"number_of_tickets":153,"number_of_unique_items":87,"is_outlier":false},{"date":"2017-04-08","store_id":1966.0,"total_sales":2897.07,"total_items_sold":233.0,"number_of_tickets":199,"number_of_unique_items":107,"is_outlier":false},{"date":"2017-04-09","store_id":1966.0,"total_sales":2430.5,"total_items_sold":194.0,"number_of_tickets":174,"number_of_unique_items":100,"is_outlier":false},{"date":"2017-04-10","store_id":1966.0,"total_sales":2103.5,"total_items_sold":153.0,"number_of_tickets":143,"number_of_unique_items":80,"is_outlier":false},{"date":"2017-04-11","store_id":1966.0,"total_sales":2155.5,"total_items_sold":169.0,"number_of_tickets":156,"number_of_unique_items":90,"is_outlier":false},{"date":"2017-04-12","store_id":1966.0,"total_sales":2209.5,"total_items_sold":172.0,"number_of_tickets":155,"number_of_unique_items":85,"is_outlier":false},{"date":"2017-04-13","store_id":1966.0,"total_sales":2818.5,"total_items_sold":224.0,"number_of_tickets":200,"number_of_unique_items":110,"is_outlier":false},{"date":"2017-04-14","store_id":1966.0,"total_sales":3208.5,"total_items_sold":269.0,"number_of_tickets":239,"number_of_unique_items":127,"is_outlier":false},{"date":"2017-04-15","store_id":1966.0,"total_sales":2679.5,"total_items_sold":212.0,"number_of_tickets":175,"number_of_unique_items":104,"is_outlier":false},{"date":"2017-04-16","store_id":1966.0,"total_sales":2163.5,"total_items_sold":164.0,"number_of_tickets":147,"number_of_unique_items":85,"is_outlier":false},{"date":"2017-04-17","store_id":1966.0,"total_sales":1712.5,"total_items_sold":145.0,"number_of_tickets":134,"number_of_unique_items":84,"is_outlier":false},{"date":"2017-04-18","store_id":1966.0,"total_sales":1897.75,"total_items_sold":143.0,"number_of_tickets":129,"number_of_unique_items":80,"is_outlier":false},{"date":"2017-04-19","store_id":1966.0,"total_sales":1684.5,"total_items_sold":128.0,"number_of_tickets":117,"number_of_unique_items":80,"is_outlier":false},{"date":"2017-04-20","store_id":1966.0,"total_sales":2491.0,"total_items_sold":172.0,"number_of_tickets":160,"number_of_unique_items":86,"is_outlier":false},{"date":"2017-04-21","store_id":1966.0,"total_sales":3475.5,"total_items_sold":208.0,"number_of_tickets":161,"number_of_unique_items":105,"is_outlier":false},{"date":"2017-04-22","store_id":1966.0,"total_sales":3748.75,"total_items_sold":242.0,"number_of_tickets":183,"number_of_unique_items":97,"is_outlier":false},{"date":"2017-04-23","store_id":1966.0,"total_sales":2316.94,"total_items_sold":175.0,"number_of_tickets":157,"number_of_unique_items":88,"is_outlier":false},{"date":"2017-04-24","store_id":1966.0,"total_sales":1598.0,"total_items_sold":114.0,"number_of_tickets":106,"number_of_unique_items":68,"is_outlier":false},{"date":"2017-04-25","store_id":1966.0,"total_sales":1661.0,"total_items_sold":116.0,"number_of_tickets":112,"number_of_unique_items":78,"is_outlier":false},{"date":"2017-04-26","store_id":1966.0,"total_sales":2017.92,"total_items_sold":153.0,"number_of_tickets":146,"number_of_unique_items":89,"is_outlier":false},{"date":"2017-04-27","store_id":1966.0,"total_sales":2083.45,"total_items_sold":158.0,"number_of_tickets":140,"number_of_unique_items":88,"is_outlier":false},{"date":"2017-04-28","store_id":1966.0,"total_sales":2790.96,"total_items_sold":208.0,"number_of_tickets":189,"number_of_unique_items":103,"is_outlier":false},{"date":"2017-04-29","store_id":1966.0,"total_sales":4001.97,"total_items_sold":250.0,"number_of_tickets":207,"number_of_unique_items":114,"is_outlier":false},{"date":"2017-04-30","store_id":1966.0,"total_sales":1943.29,"total_items_sold":151.0,"number_of_tickets":141,"number_of_unique_items":86,"is_outlier":false},{"date":"2017-05-01","store_id":1966.0,"total_sales":3965.97,"total_items_sold":200.0,"number_of_tickets":160,"number_of_unique_items":89,"is_outlier":false},{"date":"2017-05-02","store_id":1966.0,"total_sales":2091.44,"total_items_sold":162.0,"number_of_tickets":151,"number_of_unique_items":89,"is_outlier":false},{"date":"2017-05-03","store_id":1966.0,"total_sales":1943.88,"total_items_sold":155.0,"number_of_tickets":142,"number_of_unique_items":81,"is_outlier":false},{"date":"2017-05-04","store_id":1966.0,"total_sales":2286.49,"total_items_sold":162.0,"number_of_tickets":137,"number_of_unique_items":84,"is_outlier":false},{"date":"2017-05-05","store_id":1966.0,"total_sales":2038.28,"total_items_sold":154.0,"number_of_tickets":139,"number_of_unique_items":84,"is_outlier":false},{"date":"2017-05-06","store_id":1966.0,"total_sales":3128.99,"total_items_sold":230.0,"number_of_tickets":195,"number_of_unique_items":111,"is_outlier":false},{"date":"2017-05-07","store_id":1966.0,"total_sales":2056.97,"total_items_sold":160.0,"number_of_tickets":145,"number_of_unique_items":89,"is_outlier":false},{"date":"2017-05-08","store_id":1966.0,"total_sales":1672.94,"total_items_sold":129.0,"number_of_tickets":112,"number_of_unique_items":69,"is_outlier":false},{"date":"2017-05-09","store_id":1966.0,"total_sales":1937.46,"total_items_sold":158.0,"number_of_tickets":144,"number_of_unique_items":84,"is_outlier":false},{"date":"2017-05-10","store_id":1966.0,"total_sales":2009.92,"total_items_sold":156.0,"number_of_tickets":145,"number_of_unique_items":77,"is_outlier":false},{"date":"2017-05-11","store_id":1966.0,"total_sales":2353.91,"total_items_sold":186.0,"number_of_tickets":162,"number_of_unique_items":86,"is_outlier":false},{"date":"2017-05-12","store_id":1966.0,"total_sales":3016.46,"total_items_sold":218.0,"number_of_tickets":192,"number_of_unique_items":97,"is_outlier":false},{"date":"2017-05-13","store_id":1966.0,"total_sales":3316.18,"total_items_sold":183.0,"number_of_tickets":144,"number_of_unique_items":92,"is_outlier":false},{"date":"2017-05-14","store_id":1966.0,"total_sales":2477.98,"total_items_sold":171.0,"number_of_tickets":159,"number_of_unique_items":90,"is_outlier":false},{"date":"2017-05-15","store_id":1966.0,"total_sales":1657.95,"total_items_sold":127.0,"number_of_tickets":117,"number_of_unique_items":69,"is_outlier":false},{"date":"2017-05-16","store_id":1966.0,"total_sales":2712.47,"total_items_sold":189.0,"number_of_tickets":169,"number_of_unique_items":91,"is_outlier":false},{"date":"2017-05-17","store_id":1966.0,"total_sales":2701.33,"total_items_sold":170.0,"number_of_tickets":141,"number_of_unique_items":75,"is_outlier":false},{"date":"2017-05-18","store_id":1966.0,"total_sales":2611.48,"total_items_sold":199.0,"number_of_tickets":183,"number_of_unique_items":101,"is_outlier":false},{"date":"2017-05-19","store_id":1966.0,"total_sales":2822.93,"total_items_sold":230.0,"number_of_tickets":208,"number_of_unique_items":119,"is_outlier":false},{"date":"2017-05-20","store_id":1966.0,"total_sales":3877.07,"total_items_sold":214.0,"number_of_tickets":163,"number_of_unique_items":98,"is_outlier":false},{"date":"2017-05-21","store_id":1966.0,"total_sales":2056.98,"total_items_sold":162.0,"number_of_tickets":147,"number_of_unique_items":86,"is_outlier":false},{"date":"2017-05-22","store_id":1966.0,"total_sales":1247.49,"total_items_sold":103.0,"number_of_tickets":97,"number_of_unique_items":62,"is_outlier":false},{"date":"2017-05-23","store_id":1966.0,"total_sales":1894.94,"total_items_sold":148.0,"number_of_tickets":139,"number_of_unique_items":83,"is_outlier":false},{"date":"2017-05-24","store_id":1966.0,"total_sales":1822.46,"total_items_sold":138.0,"number_of_tickets":126,"number_of_unique_items":74,"is_outlier":false},{"date":"2017-05-25","store_id":1966.0,"total_sales":1726.97,"total_items_sold":130.0,"number_of_tickets":117,"number_of_unique_items":73,"is_outlier":false},{"date":"2017-05-26","store_id":1966.0,"total_sales":2702.98,"total_items_sold":231.0,"number_of_tickets":199,"number_of_unique_items":117,"is_outlier":false},{"date":"2017-05-27","store_id":1966.0,"total_sales":2811.0,"total_items_sold":211.0,"number_of_tickets":182,"number_of_unique_items":109,"is_outlier":false},{"date":"2017-05-28","store_id":1966.0,"total_sales":3230.48,"total_items_sold":179.0,"number_of_tickets":145,"number_of_unique_items":96,"is_outlier":false},{"date":"2017-05-29","store_id":1966.0,"total_sales":2021.99,"total_items_sold":151.0,"number_of_tickets":131,"number_of_unique_items":85,"is_outlier":false},{"date":"2017-05-30","store_id":1966.0,"total_sales":3690.65,"total_items_sold":135.0,"number_of_tickets":120,"number_of_unique_items":76,"is_outlier":false},{"date":"2017-05-31","store_id":1966.0,"total_sales":3033.97,"total_items_sold":187.0,"number_of_tickets":144,"number_of_unique_items":91,"is_outlier":false},{"date":"2017-06-01","store_id":1966.0,"total_sales":2002.16,"total_items_sold":165.0,"number_of_tickets":148,"number_of_unique_items":96,"is_outlier":false},{"date":"2017-06-02","store_id":1966.0,"total_sales":2843.95,"total_items_sold":227.0,"number_of_tickets":200,"number_of_unique_items":115,"is_outlier":false},{"date":"2017-06-03","store_id":1966.0,"total_sales":3380.97,"total_items_sold":210.0,"number_of_tickets":173,"number_of_unique_items":105,"is_outlier":false},{"date":"2017-06-04","store_id":1966.0,"total_sales":2383.48,"total_items_sold":182.0,"number_of_tickets":164,"number_of_unique_items":91,"is_outlier":false},{"date":"2017-06-05","store_id":1966.0,"total_sales":1902.47,"total_items_sold":140.0,"number_of_tickets":119,"number_of_unique_items":74,"is_outlier":false},{"date":"2017-06-06","store_id":1966.0,"total_sales":3399.99,"total_items_sold":56.0,"number_of_tickets":44,"number_of_unique_items":28,"is_outlier":false},{"date":"2017-06-07","store_id":1966.0,"total_sales":2478.93,"total_items_sold":189.0,"number_of_tickets":169,"number_of_unique_items":105,"is_outlier":false},{"date":"2017-06-08","store_id":1966.0,"total_sales":2031.96,"total_items_sold":168.0,"number_of_tickets":145,"number_of_unique_items":87,"is_outlier":false},{"date":"2017-06-09","store_id":1966.0,"total_sales":2558.45,"total_items_sold":222.0,"number_of_tickets":194,"number_of_unique_items":115,"is_outlier":false},{"date":"2017-06-10","store_id":1966.0,"total_sales":3548.17,"total_items_sold":207.0,"number_of_tickets":180,"number_of_unique_items":105,"is_outlier":false},{"date":"2017-06-11","store_id":1966.0,"total_sales":1944.96,"total_items_sold":155.0,"number_of_tickets":138,"number_of_unique_items":87,"is_outlier":false},{"date":"2017-06-12","store_id":1966.0,"total_sales":1853.96,"total_items_sold":151.0,"number_of_tickets":130,"number_of_unique_items":83,"is_outlier":false},{"date":"2017-06-13","store_id":1966.0,"total_sales":1716.42,"total_items_sold":143.0,"number_of_tickets":138,"number_of_unique_items":76,"is_outlier":false},{"date":"2017-06-14","store_id":1966.0,"total_sales":2366.41,"total_items_sold":196.0,"number_of_tickets":179,"number_of_unique_items":107,"is_outlier":false},{"date":"2017-06-15","store_id":1966.0,"total_sales":2125.97,"total_items_sold":171.0,"number_of_tickets":154,"number_of_unique_items":91,"is_outlier":false},{"date":"2017-06-16","store_id":1966.0,"total_sales":2745.43,"total_items_sold":209.0,"number_of_tickets":180,"number_of_unique_items":107,"is_outlier":false},{"date":"2017-06-17","store_id":1966.0,"total_sales":3077.16,"total_items_sold":206.0,"number_of_tickets":166,"number_of_unique_items":102,"is_outlier":false},{"date":"2017-06-18","store_id":1966.0,"total_sales":2017.49,"total_items_sold":160.0,"number_of_tickets":151,"number_of_unique_items":102,"is_outlier":false},{"date":"2017-06-19","store_id":1966.0,"total_sales":1751.5,"total_items_sold":107.0,"number_of_tickets":102,"number_of_unique_items":79,"is_outlier":false},{"date":"2017-06-20","store_id":1966.0,"total_sales":1995.85,"total_items_sold":146.0,"number_of_tickets":127,"number_of_unique_items":88,"is_outlier":false},{"date":"2017-06-21","store_id":1966.0,"total_sales":2318.96,"total_items_sold":188.0,"number_of_tickets":167,"number_of_unique_items":100,"is_outlier":false},{"date":"2017-06-22","store_id":1966.0,"total_sales":2073.97,"total_items_sold":158.0,"number_of_tickets":143,"number_of_unique_items":90,"is_outlier":false},{"date":"2017-06-23","store_id":1966.0,"total_sales":2664.59,"total_items_sold":199.0,"number_of_tickets":177,"number_of_unique_items":104,"is_outlier":false},{"date":"2017-06-24","store_id":1966.0,"total_sales":2962.98,"total_items_sold":223.0,"number_of_tickets":190,"number_of_unique_items":116,"is_outlier":false},{"date":"2017-06-25","store_id":1966.0,"total_sales":2953.99,"total_items_sold":216.0,"number_of_tickets":158,"number_of_unique_items":88,"is_outlier":false},{"date":"2017-06-26","store_id":1966.0,"total_sales":1584.98,"total_items_sold":119.0,"number_of_tickets":111,"number_of_unique_items":78,"is_outlier":false},{"date":"2017-06-27","store_id":1966.0,"total_sales":2026.94,"total_items_sold":157.0,"number_of_tickets":146,"number_of_unique_items":86,"is_outlier":false},{"date":"2017-06-28","store_id":1966.0,"total_sales":1841.95,"total_items_sold":154.0,"number_of_tickets":126,"number_of_unique_items":81,"is_outlier":false},{"date":"2017-06-29","store_id":1966.0,"total_sales":2040.96,"total_items_sold":153.0,"number_of_tickets":145,"number_of_unique_items":90,"is_outlier":false},{"date":"2017-06-30","store_id":1966.0,"total_sales":2517.96,"total_items_sold":202.0,"number_of_tickets":184,"number_of_unique_items":105,"is_outlier":false},{"date":"2017-07-01","store_id":1966.0,"total_sales":1941.01,"total_items_sold":151.0,"number_of_tickets":131,"number_of_unique_items":88,"is_outlier":false},{"date":"2017-07-02","store_id":1966.0,"total_sales":1991.0,"total_items_sold":145.0,"number_of_tickets":129,"number_of_unique_items":84,"is_outlier":false},{"date":"2017-07-03","store_id":1966.0,"total_sales":2040.98,"total_items_sold":172.0,"number_of_tickets":142,"number_of_unique_items":92,"is_outlier":false},{"date":"2017-07-04","store_id":1966.0,"total_sales":1320.92,"total_items_sold":101.0,"number_of_tickets":96,"number_of_unique_items":61,"is_outlier":false},{"date":"2017-07-05","store_id":1966.0,"total_sales":1725.0,"total_items_sold":131.0,"number_of_tickets":122,"number_of_unique_items":82,"is_outlier":false},{"date":"2017-07-06","store_id":1966.0,"total_sales":4947.97,"total_items_sold":172.0,"number_of_tickets":114,"number_of_unique_items":74,"is_outlier":false},{"date":"2017-07-07","store_id":1966.0,"total_sales":2318.45,"total_items_sold":177.0,"number_of_tickets":158,"number_of_unique_items":92,"is_outlier":false},{"date":"2017-07-08","store_id":1966.0,"total_sales":2334.0,"total_items_sold":160.0,"number_of_tickets":139,"number_of_unique_items":88,"is_outlier":false},{"date":"2017-07-09","store_id":1966.0,"total_sales":2187.98,"total_items_sold":150.0,"number_of_tickets":139,"number_of_unique_items":86,"is_outlier":false},{"date":"2017-07-10","store_id":1966.0,"total_sales":1558.94,"total_items_sold":125.0,"number_of_tickets":117,"number_of_unique_items":83,"is_outlier":false},{"date":"2017-07-11","store_id":1966.0,"total_sales":1749.99,"total_items_sold":130.0,"number_of_tickets":122,"number_of_unique_items":82,"is_outlier":false},{"date":"2017-07-12","store_id":1966.0,"total_sales":2331.97,"total_items_sold":159.0,"number_of_tickets":137,"number_of_unique_items":87,"is_outlier":false},{"date":"2017-07-13","store_id":1966.0,"total_sales":2139.93,"total_items_sold":183.0,"number_of_tickets":163,"number_of_unique_items":93,"is_outlier":false},{"date":"2017-07-14","store_id":1966.0,"total_sales":2164.48,"total_items_sold":177.0,"number_of_tickets":162,"number_of_unique_items":98,"is_outlier":false},{"date":"2017-07-15","store_id":1966.0,"total_sales":2769.5,"total_items_sold":198.0,"number_of_tickets":176,"number_of_unique_items":103,"is_outlier":false},{"date":"2017-07-16","store_id":1966.0,"total_sales":2269.0,"total_items_sold":178.0,"number_of_tickets":154,"number_of_unique_items":95,"is_outlier":false},{"date":"2017-07-17","store_id":1966.0,"total_sales":2045.96,"total_items_sold":156.0,"number_of_tickets":139,"number_of_unique_items":85,"is_outlier":false},{"date":"2017-07-18","store_id":1966.0,"total_sales":1792.44,"total_items_sold":136.0,"number_of_tickets":129,"number_of_unique_items":87,"is_outlier":false},{"date":"2017-07-19","store_id":1966.0,"total_sales":1608.97,"total_items_sold":133.0,"number_of_tickets":123,"number_of_unique_items":80,"is_outlier":true},{"date":"2017-07-20","store_id":1966.0,"total_sales":4369.95,"total_items_sold":176.0,"number_of_tickets":129,"number_of_unique_items":83,"is_outlier":false},{"date":"2017-07-21","store_id":1966.0,"total_sales":6187.92,"total_items_sold":207.0,"number_of_tickets":177,"number_of_unique_items":98,"is_outlier":false},{"date":"2017-07-22","store_id":1966.0,"total_sales":2442.0,"total_items_sold":176.0,"number_of_tickets":155,"number_of_unique_items":104,"is_outlier":false},{"date":"2017-07-23","store_id":1966.0,"total_sales":1878.0,"total_items_sold":133.0,"number_of_tickets":114,"number_of_unique_items":80,"is_outlier":false},{"date":"2017-07-24","store_id":1966.0,"total_sales":1741.97,"total_items_sold":135.0,"number_of_tickets":123,"number_of_unique_items":80,"is_outlier":false},{"date":"2017-07-25","store_id":1966.0,"total_sales":1937.95,"total_items_sold":152.0,"number_of_tickets":135,"number_of_unique_items":87,"is_outlier":false},{"date":"2017-07-26","store_id":1966.0,"total_sales":1905.49,"total_items_sold":159.0,"number_of_tickets":145,"number_of_unique_items":87,"is_outlier":false},{"date":"2017-07-27","store_id":1966.0,"total_sales":2190.96,"total_items_sold":163.0,"number_of_tickets":149,"number_of_unique_items":81,"is_outlier":false},{"date":"2017-07-28","store_id":1966.0,"total_sales":3206.98,"total_items_sold":203.0,"number_of_tickets":182,"number_of_unique_items":110,"is_outlier":false},{"date":"2017-07-29","store_id":1966.0,"total_sales":2757.99,"total_items_sold":204.0,"number_of_tickets":181,"number_of_unique_items":107,"is_outlier":false},{"date":"2017-07-30","store_id":1966.0,"total_sales":2251.94,"total_items_sold":188.0,"number_of_tickets":167,"number_of_unique_items":93,"is_outlier":false},{"date":"2017-07-31","store_id":1966.0,"total_sales":2104.96,"total_items_sold":155.0,"number_of_tickets":131,"number_of_unique_items":76,"is_outlier":false},{"date":"2017-08-01","store_id":1966.0,"total_sales":2133.96,"total_items_sold":167.0,"number_of_tickets":151,"number_of_unique_items":100,"is_outlier":false},{"date":"2017-08-02","store_id":1966.0,"total_sales":2102.93,"total_items_sold":150.0,"number_of_tickets":134,"number_of_unique_items":80,"is_outlier":false},{"date":"2017-08-03","store_id":1966.0,"total_sales":2063.93,"total_items_sold":166.0,"number_of_tickets":151,"number_of_unique_items":104,"is_outlier":false},{"date":"2017-08-04","store_id":1966.0,"total_sales":2280.58,"total_items_sold":175.0,"number_of_tickets":145,"number_of_unique_items":93,"is_outlier":false},{"date":"2017-08-05","store_id":1966.0,"total_sales":2495.5,"total_items_sold":190.0,"number_of_tickets":167,"number_of_unique_items":99,"is_outlier":false},{"date":"2017-08-06","store_id":1966.0,"total_sales":3057.44,"total_items_sold":174.0,"number_of_tickets":145,"number_of_unique_items":85,"is_outlier":false},{"date":"2017-08-07","store_id":1966.0,"total_sales":1317.45,"total_items_sold":113.0,"number_of_tickets":101,"number_of_unique_items":68,"is_outlier":false},{"date":"2017-08-08","store_id":1966.0,"total_sales":2142.98,"total_items_sold":179.0,"number_of_tickets":164,"number_of_unique_items":97,"is_outlier":false},{"date":"2017-08-09","store_id":1966.0,"total_sales":2162.99,"total_items_sold":154.0,"number_of_tickets":142,"number_of_unique_items":86,"is_outlier":false},{"date":"2017-08-10","store_id":1966.0,"total_sales":2060.98,"total_items_sold":159.0,"number_of_tickets":140,"number_of_unique_items":82,"is_outlier":false},{"date":"2017-08-11","store_id":1966.0,"total_sales":2625.47,"total_items_sold":192.0,"number_of_tickets":171,"number_of_unique_items":105,"is_outlier":false},{"date":"2017-08-12","store_id":1966.0,"total_sales":2886.49,"total_items_sold":189.0,"number_of_tickets":165,"number_of_unique_items":104,"is_outlier":false},{"date":"2017-08-13","store_id":1966.0,"total_sales":1817.5,"total_items_sold":140.0,"number_of_tickets":132,"number_of_unique_items":85,"is_outlier":false},{"date":"2017-08-14","store_id":1966.0,"total_sales":2175.96,"total_items_sold":149.0,"number_of_tickets":133,"number_of_unique_items":81,"is_outlier":false},{"date":"2017-08-15","store_id":1966.0,"total_sales":1912.84,"total_items_sold":137.0,"number_of_tickets":123,"number_of_unique_items":79,"is_outlier":false},{"date":"2017-08-16","store_id":1966.0,"total_sales":2111.99,"total_items_sold":160.0,"number_of_tickets":151,"number_of_unique_items":91,"is_outlier":false},{"date":"2017-08-17","store_id":1966.0,"total_sales":2106.95,"total_items_sold":168.0,"number_of_tickets":161,"number_of_unique_items":94,"is_outlier":false},{"date":"2017-08-18","store_id":1966.0,"total_sales":2461.95,"total_items_sold":172.0,"number_of_tickets":158,"number_of_unique_items":90,"is_outlier":false},{"date":"2017-08-19","store_id":1966.0,"total_sales":2602.99,"total_items_sold":188.0,"number_of_tickets":158,"number_of_unique_items":95,"is_outlier":false},{"date":"2017-08-20","store_id":1966.0,"total_sales":1773.48,"total_items_sold":142.0,"number_of_tickets":128,"number_of_unique_items":78,"is_outlier":false},{"date":"2017-08-21","store_id":1966.0,"total_sales":1744.95,"total_items_sold":132.0,"number_of_tickets":122,"number_of_unique_items":86,"is_outlier":false},{"date":"2017-08-22","store_id":1966.0,"total_sales":1625.0,"total_items_sold":128.0,"number_of_tickets":115,"number_of_unique_items":76,"is_outlier":false},{"date":"2017-08-23","store_id":1966.0,"total_sales":2184.3,"total_items_sold":180.0,"number_of_tickets":160,"number_of_unique_items":90,"is_outlier":false},{"date":"2017-08-24","store_id":1966.0,"total_sales":1939.93,"total_items_sold":152.0,"number_of_tickets":141,"number_of_unique_items":86,"is_outlier":false},{"date":"2017-08-25","store_id":1966.0,"total_sales":2432.96,"total_items_sold":182.0,"number_of_tickets":161,"number_of_unique_items":83,"is_outlier":false},{"date":"2017-08-26","store_id":1966.0,"total_sales":2347.63,"total_items_sold":169.0,"number_of_tickets":146,"number_of_unique_items":91,"is_outlier":false},{"date":"2017-08-27","store_id":1966.0,"total_sales":1843.0,"total_items_sold":139.0,"number_of_tickets":128,"number_of_unique_items":83,"is_outlier":false},{"date":"2017-08-28","store_id":1966.0,"total_sales":2069.99,"total_items_sold":159.0,"number_of_tickets":144,"number_of_unique_items":89,"is_outlier":false},{"date":"2017-08-29","store_id":1966.0,"total_sales":1584.87,"total_items_sold":128.0,"number_of_tickets":113,"number_of_unique_items":73,"is_outlier":false},{"date":"2017-08-30","store_id":1966.0,"total_sales":2129.99,"total_items_sold":155.0,"number_of_tickets":143,"number_of_unique_items":94,"is_outlier":false},{"date":"2017-08-31","store_id":1966.0,"total_sales":2134.46,"total_items_sold":165.0,"number_of_tickets":145,"number_of_unique_items":84,"is_outlier":false},{"date":"2017-09-01","store_id":1966.0,"total_sales":2133.98,"total_items_sold":172.0,"number_of_tickets":154,"number_of_unique_items":97,"is_outlier":false},{"date":"2017-09-02","store_id":1966.0,"total_sales":2127.5,"total_items_sold":153.0,"number_of_tickets":135,"number_of_unique_items":79,"is_outlier":false},{"date":"2017-09-03","store_id":1966.0,"total_sales":1958.0,"total_items_sold":147.0,"number_of_tickets":139,"number_of_unique_items":90,"is_outlier":false},{"date":"2017-09-04","store_id":1966.0,"total_sales":2047.98,"total_items_sold":154.0,"number_of_tickets":137,"number_of_unique_items":87,"is_outlier":false},{"date":"2017-09-05","store_id":1966.0,"total_sales":1599.98,"total_items_sold":121.0,"number_of_tickets":114,"number_of_unique_items":84,"is_outlier":false},{"date":"2017-09-06","store_id":1966.0,"total_sales":1707.9,"total_items_sold":124.0,"number_of_tickets":112,"number_of_unique_items":74,"is_outlier":false},{"date":"2017-09-07","store_id":1966.0,"total_sales":2169.46,"total_items_sold":127.0,"number_of_tickets":123,"number_of_unique_items":76,"is_outlier":false},{"date":"2017-09-08","store_id":1966.0,"total_sales":2478.49,"total_items_sold":185.0,"number_of_tickets":165,"number_of_unique_items":106,"is_outlier":false},{"date":"2017-09-09","store_id":1966.0,"total_sales":3015.99,"total_items_sold":214.0,"number_of_tickets":177,"number_of_unique_items":97,"is_outlier":false},{"date":"2017-09-10","store_id":1966.0,"total_sales":2086.49,"total_items_sold":160.0,"number_of_tickets":145,"number_of_unique_items":81,"is_outlier":false},{"date":"2017-09-11","store_id":1966.0,"total_sales":1635.95,"total_items_sold":135.0,"number_of_tickets":120,"number_of_unique_items":72,"is_outlier":false},{"date":"2017-09-12","store_id":1966.0,"total_sales":1914.44,"total_items_sold":163.0,"number_of_tickets":152,"number_of_unique_items":90,"is_outlier":false},{"date":"2017-09-13","store_id":1966.0,"total_sales":2724.78,"total_items_sold":263.0,"number_of_tickets":148,"number_of_unique_items":83,"is_outlier":false},{"date":"2017-09-14","store_id":1966.0,"total_sales":1620.48,"total_items_sold":141.0,"number_of_tickets":126,"number_of_unique_items":80,"is_outlier":false},{"date":"2017-09-15","store_id":1966.0,"total_sales":2494.45,"total_items_sold":198.0,"number_of_tickets":172,"number_of_unique_items":102,"is_outlier":false},{"date":"2017-09-16","store_id":1966.0,"total_sales":5766.61,"total_items_sold":215.0,"number_of_tickets":180,"number_of_unique_items":112,"is_outlier":false},{"date":"2017-09-17","store_id":1966.0,"total_sales":1715.46,"total_items_sold":132.0,"number_of_tickets":115,"number_of_unique_items":74,"is_outlier":false},{"date":"2017-09-18","store_id":1966.0,"total_sales":1754.96,"total_items_sold":132.0,"number_of_tickets":113,"number_of_unique_items":69,"is_outlier":false},{"date":"2017-09-19","store_id":1966.0,"total_sales":1605.99,"total_items_sold":123.0,"number_of_tickets":115,"number_of_unique_items":79,"is_outlier":false},{"date":"2017-09-20","store_id":1966.0,"total_sales":1684.92,"total_items_sold":135.0,"number_of_tickets":117,"number_of_unique_items":68,"is_outlier":false},{"date":"2017-09-21","store_id":1966.0,"total_sales":2010.97,"total_items_sold":154.0,"number_of_tickets":143,"number_of_unique_items":90,"is_outlier":false},{"date":"2017-09-22","store_id":1966.0,"total_sales":2824.99,"total_items_sold":213.0,"number_of_tickets":190,"number_of_unique_items":100,"is_outlier":false},{"date":"2017-09-23","store_id":1966.0,"total_sales":2043.98,"total_items_sold":170.0,"number_of_tickets":156,"number_of_unique_items":101,"is_outlier":false},{"date":"2017-09-24","store_id":1966.0,"total_sales":1601.99,"total_items_sold":134.0,"number_of_tickets":123,"number_of_unique_items":87,"is_outlier":false},{"date":"2017-09-25","store_id":1966.0,"total_sales":1433.95,"total_items_sold":123.0,"number_of_tickets":109,"number_of_unique_items":70,"is_outlier":false},{"date":"2017-09-26","store_id":1966.0,"total_sales":1915.93,"total_items_sold":153.0,"number_of_tickets":139,"number_of_unique_items":90,"is_outlier":false},{"date":"2017-09-27","store_id":1966.0,"total_sales":1793.93,"total_items_sold":150.0,"number_of_tickets":130,"number_of_unique_items":80,"is_outlier":false},{"date":"2017-09-28","store_id":1966.0,"total_sales":1393.47,"total_items_sold":117.0,"number_of_tickets":109,"number_of_unique_items":68,"is_outlier":false},{"date":"2017-09-29","store_id":1966.0,"total_sales":2322.92,"total_items_sold":190.0,"number_of_tickets":169,"number_of_unique_items":101,"is_outlier":false},{"date":"2017-09-30","store_id":1966.0,"total_sales":2936.48,"total_items_sold":219.0,"number_of_tickets":180,"number_of_unique_items":102,"is_outlier":false},{"date":"2017-10-01","store_id":1966.0,"total_sales":1695.48,"total_items_sold":129.0,"number_of_tickets":112,"number_of_unique_items":70,"is_outlier":false},{"date":"2017-10-02","store_id":1966.0,"total_sales":1599.96,"total_items_sold":132.0,"number_of_tickets":115,"number_of_unique_items":79,"is_outlier":false},{"date":"2017-10-03","store_id":1966.0,"total_sales":1456.47,"total_items_sold":119.0,"number_of_tickets":108,"number_of_unique_items":72,"is_outlier":false},{"date":"2017-10-04","store_id":1966.0,"total_sales":1849.97,"total_items_sold":138.0,"number_of_tickets":125,"number_of_unique_items":78,"is_outlier":false},{"date":"2017-10-05","store_id":1966.0,"total_sales":3515.95,"total_items_sold":137.0,"number_of_tickets":128,"number_of_unique_items":86,"is_outlier":false},{"date":"2017-10-06","store_id":1966.0,"total_sales":2204.77,"total_items_sold":183.0,"number_of_tickets":158,"number_of_unique_items":100,"is_outlier":false},{"date":"2017-10-07","store_id":1966.0,"total_sales":2806.98,"total_items_sold":195.0,"number_of_tickets":172,"number_of_unique_items":99,"is_outlier":false},{"date":"2017-10-08","store_id":1966.0,"total_sales":1924.08,"total_items_sold":144.0,"number_of_tickets":133,"number_of_unique_items":95,"is_outlier":false},{"date":"2017-10-09","store_id":1966.0,"total_sales":1170.96,"total_items_sold":101.0,"number_of_tickets":90,"number_of_unique_items":61,"is_outlier":false},{"date":"2017-10-10","store_id":1966.0,"total_sales":1345.92,"total_items_sold":107.0,"number_of_tickets":104,"number_of_unique_items":72,"is_outlier":false},{"date":"2017-10-11","store_id":1966.0,"total_sales":1873.95,"total_items_sold":188.0,"number_of_tickets":124,"number_of_unique_items":81,"is_outlier":false},{"date":"2017-10-12","store_id":1966.0,"total_sales":1506.96,"total_items_sold":114.0,"number_of_tickets":107,"number_of_unique_items":77,"is_outlier":false},{"date":"2017-10-13","store_id":1966.0,"total_sales":2379.56,"total_items_sold":193.0,"number_of_tickets":163,"number_of_unique_items":92,"is_outlier":false},{"date":"2017-10-14","store_id":1966.0,"total_sales":2602.39,"total_items_sold":200.0,"number_of_tickets":180,"number_of_unique_items":109,"is_outlier":false},{"date":"2017-10-15","store_id":1966.0,"total_sales":2002.96,"total_items_sold":150.0,"number_of_tickets":135,"number_of_unique_items":78,"is_outlier":false},{"date":"2017-10-16","store_id":1966.0,"total_sales":1416.97,"total_items_sold":108.0,"number_of_tickets":93,"number_of_unique_items":61,"is_outlier":false},{"date":"2017-10-17","store_id":1966.0,"total_sales":1665.98,"total_items_sold":120.0,"number_of_tickets":111,"number_of_unique_items":72,"is_outlier":false},{"date":"2017-10-18","store_id":1966.0,"total_sales":1628.98,"total_items_sold":128.0,"number_of_tickets":119,"number_of_unique_items":78,"is_outlier":false},{"date":"2017-10-19","store_id":1966.0,"total_sales":2216.42,"total_items_sold":210.0,"number_of_tickets":139,"number_of_unique_items":82,"is_outlier":false},{"date":"2017-10-20","store_id":1966.0,"total_sales":2504.96,"total_items_sold":191.0,"number_of_tickets":162,"number_of_unique_items":92,"is_outlier":false},{"date":"2017-10-21","store_id":1966.0,"total_sales":2732.96,"total_items_sold":206.0,"number_of_tickets":176,"number_of_unique_items":109,"is_outlier":false},{"date":"2017-10-22","store_id":1966.0,"total_sales":1592.99,"total_items_sold":123.0,"number_of_tickets":116,"number_of_unique_items":71,"is_outlier":false},{"date":"2017-10-23","store_id":1966.0,"total_sales":1434.96,"total_items_sold":120.0,"number_of_tickets":111,"number_of_unique_items":73,"is_outlier":false},{"date":"2017-10-24","store_id":1966.0,"total_sales":1211.87,"total_items_sold":103.0,"number_of_tickets":95,"number_of_unique_items":68,"is_outlier":false},{"date":"2017-10-25","store_id":1966.0,"total_sales":1668.0,"total_items_sold":131.0,"number_of_tickets":120,"number_of_unique_items":73,"is_outlier":false},{"date":"2017-10-26","store_id":1966.0,"total_sales":1773.0,"total_items_sold":130.0,"number_of_tickets":121,"number_of_unique_items":76,"is_outlier":false},{"date":"2017-10-27","store_id":1966.0,"total_sales":2197.0,"total_items_sold":162.0,"number_of_tickets":131,"number_of_unique_items":82,"is_outlier":false},{"date":"2017-10-28","store_id":1966.0,"total_sales":2663.16,"total_items_sold":198.0,"number_of_tickets":165,"number_of_unique_items":96,"is_outlier":false},{"date":"2017-10-29","store_id":1966.0,"total_sales":1500.0,"total_items_sold":109.0,"number_of_tickets":83,"number_of_unique_items":57,"is_outlier":false},{"date":"2017-10-30","store_id":1966.0,"total_sales":1541.0,"total_items_sold":112.0,"number_of_tickets":98,"number_of_unique_items":67,"is_outlier":false},{"date":"2017-10-31","store_id":1966.0,"total_sales":2930.0,"total_items_sold":162.0,"number_of_tickets":117,"number_of_unique_items":74,"is_outlier":false},{"date":"2017-11-01","store_id":1966.0,"total_sales":1700.0,"total_items_sold":125.0,"number_of_tickets":113,"number_of_unique_items":68,"is_outlier":false},{"date":"2017-11-02","store_id":1966.0,"total_sales":1952.5,"total_items_sold":153.0,"number_of_tickets":138,"number_of_unique_items":86,"is_outlier":false},{"date":"2017-11-03","store_id":1966.0,"total_sales":2600.0,"total_items_sold":199.0,"number_of_tickets":183,"number_of_unique_items":107,"is_outlier":false},{"date":"2017-11-04","store_id":1966.0,"total_sales":2562.63,"total_items_sold":175.0,"number_of_tickets":153,"number_of_unique_items":94,"is_outlier":false},{"date":"2017-11-05","store_id":1966.0,"total_sales":1514.0,"total_items_sold":120.0,"number_of_tickets":106,"number_of_unique_items":72,"is_outlier":false},{"date":"2017-11-06","store_id":1966.0,"total_sales":1057.0,"total_items_sold":74.0,"number_of_tickets":71,"number_of_unique_items":47,"is_outlier":false},{"date":"2017-11-07","store_id":1966.0,"total_sales":1352.0,"total_items_sold":102.0,"number_of_tickets":92,"number_of_unique_items":60,"is_outlier":false},{"date":"2017-11-08","store_id":1966.0,"total_sales":1783.0,"total_items_sold":123.0,"number_of_tickets":114,"number_of_unique_items":69,"is_outlier":false},{"date":"2017-11-09","store_id":1966.0,"total_sales":1720.0,"total_items_sold":125.0,"number_of_tickets":112,"number_of_unique_items":72,"is_outlier":false},{"date":"2017-11-10","store_id":1966.0,"total_sales":2095.5,"total_items_sold":160.0,"number_of_tickets":139,"number_of_unique_items":99,"is_outlier":false},{"date":"2017-11-11","store_id":1966.0,"total_sales":2362.61,"total_items_sold":187.0,"number_of_tickets":145,"number_of_unique_items":96,"is_outlier":false},{"date":"2017-11-12","store_id":1966.0,"total_sales":1893.5,"total_items_sold":134.0,"number_of_tickets":121,"number_of_unique_items":79,"is_outlier":false},{"date":"2017-11-13","store_id":1966.0,"total_sales":1414.0,"total_items_sold":114.0,"number_of_tickets":104,"number_of_unique_items":69,"is_outlier":false},{"date":"2017-11-14","store_id":1966.0,"total_sales":1634.0,"total_items_sold":121.0,"number_of_tickets":109,"number_of_unique_items":74,"is_outlier":false},{"date":"2017-11-15","store_id":1966.0,"total_sales":2094.92,"total_items_sold":135.0,"number_of_tickets":122,"number_of_unique_items":73,"is_outlier":false},{"date":"2017-11-16","store_id":1966.0,"total_sales":1791.0,"total_items_sold":122.0,"number_of_tickets":113,"number_of_unique_items":71,"is_outlier":false},{"date":"2017-11-17","store_id":1966.0,"total_sales":2693.52,"total_items_sold":176.0,"number_of_tickets":151,"number_of_unique_items":99,"is_outlier":false},{"date":"2017-11-18","store_id":1966.0,"total_sales":2478.5,"total_items_sold":182.0,"number_of_tickets":143,"number_of_unique_items":90,"is_outlier":false},{"date":"2017-11-19","store_id":1966.0,"total_sales":1862.5,"total_items_sold":123.0,"number_of_tickets":107,"number_of_unique_items":67,"is_outlier":false},{"date":"2017-11-20","store_id":1966.0,"total_sales":1977.0,"total_items_sold":136.0,"number_of_tickets":118,"number_of_unique_items":72,"is_outlier":false},{"date":"2017-11-21","store_id":1966.0,"total_sales":1936.5,"total_items_sold":133.0,"number_of_tickets":119,"number_of_unique_items":71,"is_outlier":false},{"date":"2017-11-22","store_id":1966.0,"total_sales":1455.0,"total_items_sold":99.0,"number_of_tickets":90,"number_of_unique_items":55,"is_outlier":false},{"date":"2017-11-23","store_id":1966.0,"total_sales":1046.0,"total_items_sold":87.0,"number_of_tickets":71,"number_of_unique_items":49,"is_outlier":false},{"date":"2017-11-24","store_id":1966.0,"total_sales":1531.0,"total_items_sold":120.0,"number_of_tickets":98,"number_of_unique_items":68,"is_outlier":false},{"date":"2017-11-25","store_id":1966.0,"total_sales":2257.0,"total_items_sold":152.0,"number_of_tickets":132,"number_of_unique_items":83,"is_outlier":false},{"date":"2017-11-26","store_id":1966.0,"total_sales":1494.5,"total_items_sold":105.0,"number_of_tickets":97,"number_of_unique_items":62,"is_outlier":false},{"date":"2017-11-27","store_id":1966.0,"total_sales":1382.0,"total_items_sold":98.0,"number_of_tickets":87,"number_of_unique_items":60,"is_outlier":false},{"date":"2017-11-28","store_id":1966.0,"total_sales":3939.0,"total_items_sold":138.0,"number_of_tickets":86,"number_of_unique_items":64,"is_outlier":false},{"date":"2017-11-29","store_id":1966.0,"total_sales":1724.0,"total_items_sold":125.0,"number_of_tickets":116,"number_of_unique_items":65,"is_outlier":false},{"date":"2017-11-30","store_id":1966.0,"total_sales":1542.0,"total_items_sold":114.0,"number_of_tickets":102,"number_of_unique_items":69,"is_outlier":false},{"date":"2017-12-01","store_id":1966.0,"total_sales":2634.5,"total_items_sold":205.0,"number_of_tickets":172,"number_of_unique_items":101,"is_outlier":false},{"date":"2017-12-02","store_id":1966.0,"total_sales":4357.0,"total_items_sold":253.0,"number_of_tickets":199,"number_of_unique_items":112,"is_outlier":false},{"date":"2017-12-03","store_id":1966.0,"total_sales":2102.5,"total_items_sold":152.0,"number_of_tickets":140,"number_of_unique_items":81,"is_outlier":false},{"date":"2017-12-04","store_id":1966.0,"total_sales":1322.0,"total_items_sold":99.0,"number_of_tickets":92,"number_of_unique_items":58,"is_outlier":false},{"date":"2017-12-05","store_id":1966.0,"total_sales":1490.0,"total_items_sold":115.0,"number_of_tickets":105,"number_of_unique_items":61,"is_outlier":false},{"date":"2017-12-06","store_id":1966.0,"total_sales":1431.0,"total_items_sold":111.0,"number_of_tickets":97,"number_of_unique_items":72,"is_outlier":false},{"date":"2017-12-07","store_id":1966.0,"total_sales":1277.86,"total_items_sold":105.0,"number_of_tickets":93,"number_of_unique_items":69,"is_outlier":false},{"date":"2017-12-08","store_id":1966.0,"total_sales":3765.0,"total_items_sold":206.0,"number_of_tickets":156,"number_of_unique_items":89,"is_outlier":false},{"date":"2017-12-09","store_id":1966.0,"total_sales":2886.3,"total_items_sold":178.0,"number_of_tickets":142,"number_of_unique_items":97,"is_outlier":false},{"date":"2017-12-10","store_id":1966.0,"total_sales":1905.5,"total_items_sold":141.0,"number_of_tickets":115,"number_of_unique_items":73,"is_outlier":false},{"date":"2017-12-11","store_id":1966.0,"total_sales":1404.0,"total_items_sold":98.0,"number_of_tickets":94,"number_of_unique_items":59,"is_outlier":false},{"date":"2017-12-12","store_id":1966.0,"total_sales":4464.92,"total_items_sold":123.0,"number_of_tickets":75,"number_of_unique_items":50,"is_outlier":false},{"date":"2017-12-13","store_id":1966.0,"total_sales":571.0,"total_items_sold":51.0,"number_of_tickets":48,"number_of_unique_items":32,"is_outlier":false},{"date":"2017-12-14","store_id":1966.0,"total_sales":6912.0,"total_items_sold":190.0,"number_of_tickets":130,"number_of_unique_items":81,"is_outlier":false},{"date":"2017-12-15","store_id":1966.0,"total_sales":2095.0,"total_items_sold":143.0,"number_of_tickets":116,"number_of_unique_items":76,"is_outlier":false},{"date":"2017-12-16","store_id":1966.0,"total_sales":3417.5,"total_items_sold":248.0,"number_of_tickets":191,"number_of_unique_items":111,"is_outlier":false},{"date":"2017-12-17","store_id":1966.0,"total_sales":1921.42,"total_items_sold":135.0,"number_of_tickets":124,"number_of_unique_items":77,"is_outlier":false},{"date":"2017-12-18","store_id":1966.0,"total_sales":1585.0,"total_items_sold":115.0,"number_of_tickets":108,"number_of_unique_items":71,"is_outlier":false},{"date":"2017-12-19","store_id":1966.0,"total_sales":2000.4,"total_items_sold":149.0,"number_of_tickets":132,"number_of_unique_items":83,"is_outlier":false},{"date":"2017-12-20","store_id":1966.0,"total_sales":1699.0,"total_items_sold":127.0,"number_of_tickets":111,"number_of_unique_items":68,"is_outlier":false},{"date":"2017-12-21","store_id":1966.0,"total_sales":1719.0,"total_items_sold":134.0,"number_of_tickets":121,"number_of_unique_items":82,"is_outlier":false},{"date":"2017-12-22","store_id":1966.0,"total_sales":2076.0,"total_items_sold":163.0,"number_of_tickets":137,"number_of_unique_items":83,"is_outlier":false},{"date":"2017-12-23","store_id":1966.0,"total_sales":1839.0,"total_items_sold":115.0,"number_of_tickets":102,"number_of_unique_items":76,"is_outlier":false},{"date":"2017-12-24","store_id":1966.0,"total_sales":1224.0,"total_items_sold":91.0,"number_of_tickets":80,"number_of_unique_items":56,"is_outlier":false},{"date":"2017-12-26","store_id":1966.0,"total_sales":1298.0,"total_items_sold":97.0,"number_of_tickets":87,"number_of_unique_items":63,"is_outlier":false},{"date":"2017-12-27","store_id":1966.0,"total_sales":1180.0,"total_items_sold":89.0,"number_of_tickets":85,"number_of_unique_items":60,"is_outlier":false},{"date":"2017-12-28","store_id":1966.0,"total_sales":1479.0,"total_items_sold":107.0,"number_of_tickets":92,"number_of_unique_items":69,"is_outlier":false},{"date":"2017-12-29","store_id":1966.0,"total_sales":1995.0,"total_items_sold":157.0,"number_of_tickets":125,"number_of_unique_items":94,"is_outlier":false},{"date":"2017-12-30","store_id":1966.0,"total_sales":2641.0,"total_items_sold":162.0,"number_of_tickets":146,"number_of_unique_items":89,"is_outlier":false},{"date":"2017-12-31","store_id":1966.0,"total_sales":2638.5,"total_items_sold":184.0,"number_of_tickets":126,"number_of_unique_items":74,"is_outlier":false}]